Workbook

Sheet PagosVencidos
A1: RESPONSABLE DE PAGO | B1: NRO. POLIZA | C1: CATEGORÍA | D1: DOCUMENTO | E1: MEDIO DE PAGO | F1: MONTO | G1: CUOTA | H1: VENCIMIENTO | I1: ESTADO
A2: CLUB SPORTING CRISTAL S.A. | B2: E0002259 | C2: EPS | D2: LQ 1013399824 | E2: AL CONTADO | F2: S/793.64 | G2: 1/1 | H2: 2023-05-29 | I2: Póliza por anular
A3: CLUB SPORTING CRISTAL S.A. | B3: E0002259 | C3: EPS | D3: LQ 1017717852 | E3: AL CONTADO | F3: S/2246.92 | G3: 1/1 | H3: 2023-06-16 | I3: Póliza por anular
A4: CAMPARI PERU SOCIEDAD ANONIMA CERRADA - CAMPARI PERU S.A.C. | B4: E0029631 | C4: EPS | D4: LQ 1056649472 | E4: AL CONTADO | F4: S/1574.00 | G4: 1/1 | H4: 2023-10-02 | I4: Póliza por anular
A5: CAMPARI PERU SOCIEDAD ANONIMA CERRADA - CAMPARI PERU S.A.C. | B5: E0029631 | C5: EPS | D5: LQ 1063380835 | E5: AL CONTADO | F5: S/1574.00 | G5: 1/1 | H5: 2023-11-02 | I5: Póliza por anular
A6: CAMPARI PERU SOCIEDAD ANONIMA CERRADA - CAMPARI PERU S.A.C. | B6: E0029631 | C6: EPS | D6: LQ 1070914547 | E6: AL CONTADO | F6: S/1574.00 | G6: 1/1 | H6: 2023-12-05 | I6: Póliza por anular
A7: CAMPARI PERU SOCIEDAD ANONIMA CERRADA - CAMPARI PERU S.A.C. | B7: E0029631 | C7: EPS | D7: LQ 1077067732 | E7: AL CONTADO | F7: S/1574.00 | G7: 1/1 | H7: 2024-01-04 | I7: Póliza por anular
A8: CAMPARI PERU SOCIEDAD ANONIMA CERRADA - CAMPARI PERU S.A.C. | B8: E0029631 | C8: EPS | D8: LQ 1083881434 | E8: AL CONTADO | F8: S/1574.00 | G8: 1/1 | H8: 2024-02-01 | I8: Póliza por anular
A9: CIMER INGENIEROS SAC | B9: S0350529 | C9: S.C.T.R. - SALUD | D9: LQ 1149152807 | E9: AL CONTADO | F9: S/1224.55 | G9: 1/1 | H9: 2024-12-02 | I9: Póliza por anular
A10: CIMER INGENIEROS SAC | B10: S0350529 | C10: S.C.T.R. - SALUD | D10: LQ 1155996646 | E10: AL CONTADO | F10: S/35.40 | G10: 1/1 | H10: 2024-12-06 | I10: Póliza por anular
A11: CIMER INGENIEROS SAC | B11: S0350529 | C11: S.C.T.R. - SALUD | D11: LQ 1159477167 | E11: AL CONTADO | F11: S/35.40 | G11: 1/1 | H11: 2024-12-13 | I11: Póliza por anular
A12: CIMER INGENIEROS SAC | B12: S0350529 | C12: S.C.T.R. - SALUD | D12: LQ 1659915017 | E12: AL CONTADO | F12: S/35.40 | G12: 1/1 | H12: 2024-12-19 | I12: Póliza por anular
... A1940: QUIROZ CORAL MANUEL ADOLFO | B1940: 93933 | C1940: SALUD RED MÉDICA | D1940: CC 1170971124 | E1940: DÉBITO AUTOMÁTICO | F1940: S/286.48 | G1940: 12/12 | H1940: 2026-11-08 | I1940: Pago por vencer

Sheet Hoja2
A1: RESPONSABLE DE PAGO | B1: NRO. POLIZA | C1: CATEGORÍA | D1: VENCIMIENTO
A2: CLUB SPORTING CRISTAL S.A. | B2: E0002259 | C2: EPS | D2: =VLOOKUP(B2,PagosVencidos!$B$1:$H$1940,7,0) -> 2023-05-29
A3: CAMPARI PERU SOCIEDAD ANONIMA CERRADA - CAMPARI PERU S.A.C. | B3: E0029631 | C3: EPS | D3: =VLOOKUP(B3,PagosVencidos!$B$1:$H$1940,7,0) -> 2023-10-02
A4: CIMER INGENIEROS SAC | B4: S0350529 | C4: S.C.T.R. - SALUD | D4: =VLOOKUP(B4,PagosVencidos!$B$1:$H$1940,7,0) -> 2024-12-02
A5: DIGITAL BUSINESS PERU S.A.C. | B5: E0004449 | C5: EPS | D5: =VLOOKUP(B5,PagosVencidos!$B$1:$H$1940,7,0) -> 2025-02-03
A6: BELTRAN BYRNE GUILLERMO | B6: E0027232 | C6: EPS | D6: =VLOOKUP(B6,PagosVencidos!$B$1:$H$1940,7,0) -> 2025-05-07
A7: CONTRERAS IVARCENA EDUARDO DIEGO | B7: 1483595 | C7: WEB VEHICULOS | D7: =VLOOKUP(B7,PagosVencidos!$B$1:$H$1940,7,0) -> 2025-05-28
A8: SEMINARIO Y CIA S.A.B. S. A. | B8: 44936720 | C8: VIDA LEY D.L. 688 | D8: =VLOOKUP(B8,PagosVencidos!$B$1:$H$1940,7,0) -> 2025-07-11
A9: BRAVO GARCIA BELEN SARAI | B9: 67765 | C9: SALUD RED PREFERENTE | D9: =VLOOKUP(B9,PagosVencidos!$B$1:$H$1940,7,0) -> 2025-07-28
A10: INMOBILIARIA EGP S.A.C. | B10: 1544218 | C10: WEB VEHICULOS | D10: =VLOOKUP(B10,PagosVencidos!$B$1:$H$1940,7,0) -> 2025-07-29
A11: TEGA INDUSTRIES PERU S.A.C. | B11: 48599 | C11: FORMACION LABORAL | D11: =VLOOKUP(B11,PagosVencidos!$B$1:$H$1940,7,0) -> 2025-07-31
A12: DIGITAL BUSINESS PERU S.A.C. | B12: 67289811 | C12: VIDA LEY D.L. 688 | D12: =VLOOKUP(B12,PagosVencidos!$B$1:$H$1940,7,0) -> 2025-08-01
A13: VARAS RUIZ LUCIA MIREILLE | B13: E0035204 | C13: EPS | D13: =VLOOKUP(B13,PagosVencidos!$B$1:$H$1940,7,0) -> 2025-08-14
... A417: BPZ EXPLORACION & PRODUCCION S.R.L. | B417: 53662 | C417: FULLSALUD | D417: =VLOOKUP(B417,PagosVencidos!$B$1:$H$1940,7,0) -> 2025-12-31

Sheet Hoja1
A1: RESPONSABLE DE PAGO | B1: NRO. POLIZA | C1: CATEGORÍA
A2: CLUB SPORTING CRISTAL S.A. | B2: E0002259 | C2: EPS | D2: 2023-05-29
A3: CAMPARI PERU SOCIEDAD ANONIMA CERRADA - CAMPARI PERU S.A.C. | B3: E0029631 | C3: EPS | D3: 2023-10-02
A4: CIMER INGENIEROS SAC | B4: S0350529 | C4: S.C.T.R. - SALUD | D4: 2024-12-02
A5: DIGITAL BUSINESS PERU S.A.C. | B5: E0004449 | C5: EPS | D5: 2025-02-03
A6: BELTRAN BYRNE GUILLERMO | B6: E0027232 | C6: EPS | D6: 2025-05-07
A7: CONTRERAS IVARCENA EDUARDO DIEGO | B7: 1483595 | C7: WEB VEHICULOS | D7: 2025-05-28
A8: SEMINARIO Y CIA S.A.B. S. A. | B8: 44936720 | C8: VIDA LEY D.L. 688 | D8: 2025-07-11
A9: BRAVO GARCIA BELEN SARAI | B9: 67765 | C9: SALUD RED PREFERENTE | D9: 2025-07-28
A10: INMOBILIARIA EGP S.A.C. | B10: 1544218 | C10: WEB VEHICULOS | D10: 2025-07-29
A11: TEGA INDUSTRIES PERU S.A.C. | B11: 48599 | C11: FORMACION LABORAL | D11: 2025-07-31
A12: DIGITAL BUSINESS PERU S.A.C. | B12: 67289811 | C12: VIDA LEY D.L. 688 | D12: 2025-08-01
A13: VARAS RUIZ LUCIA MIREILLE | B13: E0035204 | C13: EPS | D13: 2025-08-14
... A417: BPZ EXPLORACION & PRODUCCION S.R.L. | B417: 53662 | C417: FULLSALUD | D417: 2025-12-31
