Workbook

Sheet Td_Diferencias
A4: Observaciones | B4: Briyan | C4: Cesar | D4: Jesus | E4: Total general
A5: 1. No está cargado en el SICS-Tablero | C5: 1 | D5: 4 | E5: 5
A6: 2. Actualizar la vigencia en el SICS | B6: 7 | C6: 5 | D6: 7 | E6: 19
A7: 6. Revisar renovación | C7: 2 | D7: 2 | E7: 4
A8: Total general | B8: 7 | C8: 8 | D8: 13 | E8: 28

Sheet Reporte
A1: rimac | B1: rimac | C1: SICS | D1: Tablero | G1: rimac | H1: rimac
A2: RESPONSABLE DE PAGO | B2: NRO. POLIZA | C2: SICS | D2: Tablero | E2: Observaciones | F2: Responsable | G2: CATEGORÍA | H2: VENCIMIENTO | I2: MOTIVO | J2: ASEGURADORA RENOVADA | K2: POLIZANUEVA | L2: OBSERVACIONES | M2: Obs | N2: SICS
A3: FITESA PERU S.A.C. | B3: 42982 | C3: =_xlfn.XLOOKUP(B3,[1]ReportePolizaPorFiltroArribas!$G$1:$G$3955,[1]ReportePolizaPorFiltroArribas!$O$1:$O$3955,"No Encontrado",0) -> No Encontrado | D3: =_xlfn.XLOOKUP(B3,[2]Tablero!$AP$1:$AP$6608,[2]Tablero!$AE$1:$AE$6608,"No Encontrado",0) -> No Encontrado | E3: 1. No está cargado en el SICS-Tablero | F3: =IF(E3<>"",_xlfn.XLOOKUP(G3,pivot!$B$1:$B$34,pivot!$A$1:$A$34,"",0),"") -> Jesus | G3: FORMACION LABORAL | H3: 2025-10-31 | M3: =IF(C3<=TEXT(H3,"YYYY-MM"),2,6) -> 6
A4: BALTAZAR Y NICOLAS ASOCIACIÓN CIVIL SIN FINES DE LUCRO | B4: 1300649048 | C4: =_xlfn.XLOOKUP(B4,[1]ReportePolizaPorFiltroArribas!$G$1:$G$3955,[1]ReportePolizaPorFiltroArribas!$O$1:$O$3955,"No Encontrado",0) -> No Encontrado | D4: =_xlfn.XLOOKUP(B4,[2]Tablero!$AP$1:$AP$6608,[2]Tablero!$AE$1:$AE$6608,"No Encontrado",0) -> No Encontrado | E4: 1. No está cargado en el SICS-Tablero | F4: =IF(E4<>"",_xlfn.XLOOKUP(G4,pivot!$B$1:$B$34,pivot!$A$1:$A$34,"",0),"") -> Jesus | G4: VIDALEYRE | H4: 2025-11-10 | M4: =IF(C4<=TEXT(H4,"YYYY-MM"),2,6) -> 6
A5: TELECYL PERU SAC | B5: 1300649031 | C5: =_xlfn.XLOOKUP(B5,[1]ReportePolizaPorFiltroArribas!$G$1:$G$3955,[1]ReportePolizaPorFiltroArribas!$O$1:$O$3955,"No Encontrado",0) -> No Encontrado | D5: =_xlfn.XLOOKUP(B5,[2]Tablero!$AP$1:$AP$6608,[2]Tablero!$AE$1:$AE$6608,"No Encontrado",0) -> No Encontrado | E5: 1. No está cargado en el SICS-Tablero | F5: =IF(E5<>"",_xlfn.XLOOKUP(G5,pivot!$B$1:$B$34,pivot!$A$1:$A$34,"",0),"") -> Jesus | G5: VIDALEYRE | H5: 2025-11-13 | M5: =IF(C5<=TEXT(H5,"YYYY-MM"),2,6) -> 6
A6: ELECNOR PERU S.A.C. | B6: 1300047326 | C6: =_xlfn.XLOOKUP(B6,[1]ReportePolizaPorFiltroArribas!$G$1:$G$3955,[1]ReportePolizaPorFiltroArribas!$O$1:$O$3955,"No Encontrado",0) -> No Encontrado | D6: =_xlfn.XLOOKUP(B6,[2]Tablero!$AP$1:$AP$6608,[2]Tablero!$AE$1:$AE$6608,"No Encontrado",0) -> No Encontrado | E6: 1. No está cargado en el SICS-Tablero | F6: =IF(E6<>"",_xlfn.XLOOKUP(G6,pivot!$B$1:$B$34,pivot!$A$1:$A$34,"",0),"") -> Jesus | G6: VIDA LEY D.L. 688 | H6: 2025-11-13 | M6: =IF(C6<=TEXT(H6,"YYYY-MM"),2,6) -> 6
A7: LININGS S.A. | B7: 1578645 | C7: =_xlfn.XLOOKUP(B7,[1]ReportePolizaPorFiltroArribas!$G$1:$G$3955,[1]ReportePolizaPorFiltroArribas!$O$1:$O$3955,"No Encontrado",0) -> No Encontrado | D7: =_xlfn.XLOOKUP(B7,[2]Tablero!$AP$1:$AP$6608,[2]Tablero!$AE$1:$AE$6608,"No Encontrado",0) -> No Encontrado | E7: 1. No está cargado en el SICS-Tablero | F7: =IF(E7<>"",_xlfn.XLOOKUP(G7,pivot!$B$1:$B$34,pivot!$A$1:$A$34,"",0),"") -> Cesar | G7: WEB VEHICULOS | H7: 2025-11-24 | M7: =IF(C7<=TEXT(H7,"YYYY-MM"),2,6) -> 6
A8: INTERNATIONAL 4PL CARGO S.A.C. | B8: 1300369041 | C8: =_xlfn.XLOOKUP(B8,[1]ReportePolizaPorFiltroArribas!$G$1:$G$3955,[1]ReportePolizaPorFiltroArribas!$O$1:$O$3955,"No Encontrado",0) -> 2025-09 | D8: =_xlfn.XLOOKUP(B8,[2]Tablero!$AP$1:$AP$6608,[2]Tablero!$AE$1:$AE$6608,"No Encontrado",0) -> 02 - EN PROCESO | E8: 2. Actualizar la vigencia en el SICS | F8: =IF(E8<>"",_xlfn.XLOOKUP(G8,pivot!$B$1:$B$34,pivot!$A$1:$A$34,"",0),"") -> Jesus | G8: VIDA LEY D.L. 688 | H8: 2025-09-05 | M8: =IF(C8<=TEXT(H8,"YYYY-MM"),2,6) -> 2
A9: SENCINET LATAM PERU S.A.C. | B9: 1300356735 | C9: =_xlfn.XLOOKUP(B9,[1]ReportePolizaPorFiltroArribas!$G$1:$G$3955,[1]ReportePolizaPorFiltroArribas!$O$1:$O$3955,"No Encontrado",0) -> 2025-10 | D9: =_xlfn.XLOOKUP(B9,[2]Tablero!$AP$1:$AP$6608,[2]Tablero!$AE$1:$AE$6608,"No Encontrado",0) -> 01 - RENOVADA | E9: 2. Actualizar la vigencia en el SICS | F9: =IF(E9<>"",_xlfn.XLOOKUP(G9,pivot!$B$1:$B$34,pivot!$A$1:$A$34,"",0),"") -> Jesus | G9: VIDA LEY D.L. 688 | H9: 2025-10-01 | M9: =IF(C9<=TEXT(H9,"YYYY-MM"),2,6) -> 2
A10: BYBLUE PERU SOCIEDAD ANONIMA CERRADA - BYBLUE PERU S.A.C. | B10: 1300615764 | C10: =_xlfn.XLOOKUP(B10,[1]ReportePolizaPorFiltroArribas!$G$1:$G$3955,[1]ReportePolizaPorFiltroArribas!$O$1:$O$3955,"No Encontrado",0) -> 2025-10 | D10: =_xlfn.XLOOKUP(B10,[2]Tablero!$AP$1:$AP$6608,[2]Tablero!$AE$1:$AE$6608,"No Encontrado",0) -> 01 - RENOVADA | E10: 2. Actualizar la vigencia en el SICS | F10: =IF(E10<>"",_xlfn.XLOOKUP(G10,pivot!$B$1:$B$34,pivot!$A$1:$A$34,"",0),"") -> Jesus | G10: VIDA LEY D.L. 688 | H10: 2025-10-10 | M10: =IF(C10<=TEXT(H10,"YYYY-MM"),2,6) -> 2
A11: TELECYL PERU SAC | B11: 65598970 | C11: =_xlfn.XLOOKUP(B11,[1]ReportePolizaPorFiltroArribas!$G$1:$G$3955,[1]ReportePolizaPorFiltroArribas!$O$1:$O$3955,"No Encontrado",0) -> 2025-10 | D11: =_xlfn.XLOOKUP(B11,[2]Tablero!$AP$1:$AP$6608,[2]Tablero!$AE$1:$AE$6608,"No Encontrado",0) -> 03 - PENDIENTE | E11: 2. Actualizar la vigencia en el SICS | F11: =IF(E11<>"",_xlfn.XLOOKUP(G11,pivot!$B$1:$B$34,pivot!$A$1:$A$34,"",0),"") -> Jesus | G11: VIDA LEY D.L. 688 | H11: 2025-10-10 | M11: =IF(C11<=TEXT(H11,"YYYY-MM"),2,6) -> 2
A12: LABORATORIO FARMACEUTICO SAN JOAQUIN-ROXFARMA SOCIEDAD ANONIMA | B12: 44654 | C12: =_xlfn.XLOOKUP(B12,[1]ReportePolizaPorFiltroArribas!$G$1:$G$3955,[1]ReportePolizaPorFiltroArribas!$O$1:$O$3955,"No Encontrado",0) -> 2025-10 | D12: =_xlfn.XLOOKUP(B12,[2]Tablero!$AP$1:$AP$6608,[2]Tablero!$AE$1:$AE$6608,"No Encontrado",0) -> 03 - PENDIENTE | E12: 2. Actualizar la vigencia en el SICS | F12: =IF(E12<>"",_xlfn.XLOOKUP(G12,pivot!$B$1:$B$34,pivot!$A$1:$A$34,"",0),"") -> Jesus | G12: FORMACION LABORAL | H12: 2025-10-17 | M12: =IF(C12<=TEXT(H12,"YYYY-MM"),2,6) -> 2
A13: GILES PONCE CARLOS LEONIDAS | B13: 74840 | C13: =_xlfn.XLOOKUP(B13,[1]ReportePolizaPorFiltroArribas!$G$1:$G$3955,[1]ReportePolizaPorFiltroArribas!$O$1:$O$3955,"No Encontrado",0) -> 2025-11 | D13: =_xlfn.XLOOKUP(B13,[2]Tablero!$AP$1:$AP$6608,[2]Tablero!$AE$1:$AE$6608,"No Encontrado",0) -> 03 - PENDIENTE | E13: 2. Actualizar la vigencia en el SICS | F13: =IF(E13<>"",_xlfn.XLOOKUP(G13,pivot!$B$1:$B$34,pivot!$A$1:$A$34,"",0),"") -> Briyan | G13: SALUD RED MÉDICA | H13: 2025-11-04 | M13: =IF(C13<=TEXT(H13,"YYYY-MM"),2,6) -> 2
A14: FLOR TORO JOSE LUIS | B14: 456784 | C14: =_xlfn.XLOOKUP(B14,[1]ReportePolizaPorFiltroArribas!$G$1:$G$3955,[1]ReportePolizaPorFiltroArribas!$O$1:$O$3955,"No Encontrado",0) -> 2025-11 | D14: =_xlfn.XLOOKUP(B14,[2]Tablero!$AP$1:$AP$6608,[2]Tablero!$AE$1:$AE$6608,"No Encontrado",0) -> 01 - RENOVADA | E14: 2. Actualizar la vigencia en el SICS | F14: =IF(E14<>"",_xlfn.XLOOKUP(G14,pivot!$B$1:$B$34,pivot!$A$1:$A$34,"",0),"") -> Cesar | G14: WEB VEHICULOS | H14: 2025-11-15 | M14: =IF(C14<=TEXT(H14,"YYYY-MM"),2,6) -> 2
... A24: BPZ EXPLORACION & PRODUCCION S.R.L. | B24: 53662 | C24: =_xlfn.XLOOKUP(B24,[1]ReportePolizaPorFiltroArribas!$G$1:$G$3955,[1]ReportePolizaPorFiltroArribas!$O$1:$O$3955,"No Encontrado",0) -> 2025-11 | D24: =_xlfn.XLOOKUP(B24,[2]Tablero!$AP$1:$AP$6608,[2]Tablero!$AE$1:$AE$6608,"No Encontrado",0) -> 03 - PENDIENTE | E24: 2. Actualizar la vigencia en el SICS | F24: =IF(E24<>"",_xlfn.XLOOKUP(G24,pivot!$B$1:$B$34,pivot!$A$1:$A$34,"",0),"") -> Briyan | G24: FULLSALUD | H24: 2025-12-31 | M24: =IF(C24<=TEXT(H24,"YYYY-MM"),2,6) -> 2
A25: IMPRESSO GRAFICA S A | B25: E0001323 | C25: =_xlfn.XLOOKUP(B25,[1]ReportePolizaPorFiltroArribas!$G$1:$G$3955,[1]ReportePolizaPorFiltroArribas!$O$1:$O$3955,"No Encontrado",0) -> 2025-10 | D25: =_xlfn.XLOOKUP(B25,[2]Tablero!$AP$1:$AP$6608,[2]Tablero!$AE$1:$AE$6608,"No Encontrado",0) -> No Encontrado | E25: 2. Actualizar la vigencia en el SICS | F25: =IF(E25<>"",_xlfn.XLOOKUP(G25,pivot!$B$1:$B$34,pivot!$A$1:$A$34,"",0),"") -> Briyan | G25: EPS | H25: 2025-11-03 | M25: =IF(C25<=TEXT(H25,"YYYY-MM"),2,6) -> 2
A26: LININGS S.A. | B26: 1581063 | C26: =_xlfn.XLOOKUP(B26,[1]ReportePolizaPorFiltroArribas!$G$1:$G$3955,[1]ReportePolizaPorFiltroArribas!$O$1:$O$3955,"No Encontrado",0) -> 2025-10 | D26: =_xlfn.XLOOKUP(B26,[2]Tablero!$AP$1:$AP$6608,[2]Tablero!$AE$1:$AE$6608,"No Encontrado",0) -> 01 - RENOVADA | E26: 2. Actualizar la vigencia en el SICS | F26: =IF(E26<>"",_xlfn.XLOOKUP(G26,pivot!$B$1:$B$34,pivot!$A$1:$A$34,"",0),"") -> Cesar | G26: WEB VEHICULOS | H26: 2025-11-24 | M26: =IF(C26<=TEXT(H26,"YYYY-MM"),2,6) -> 2
A27: SEMINARIO Y CIA S.A.B. S. A. | B27: 44936720 | C27: =_xlfn.XLOOKUP(B27,[1]ReportePolizaPorFiltroArribas!$G$1:$G$3955,[1]ReportePolizaPorFiltroArribas!$O$1:$O$3955,"No Encontrado",0) -> 2025-10 | D27: =_xlfn.XLOOKUP(B27,[2]Tablero!$AP$1:$AP$6608,[2]Tablero!$AE$1:$AE$6608,"No Encontrado",0) -> 03 - PENDIENTE | E27: 6. Revisar renovación | F27: =IF(E27<>"",_xlfn.XLOOKUP(G27,pivot!$B$1:$B$34,pivot!$A$1:$A$34,"",0),"") -> Jesus | G27: VIDA LEY D.L. 688 | H27: 2025-07-11 | M27: =IF(C27<=TEXT(H27,"YYYY-MM"),2,6) -> 6
A28: XIAOMI TECHNOLOGIES PERU S.A.C. | B28: 48411 | C28: =_xlfn.XLOOKUP(B28,[1]ReportePolizaPorFiltroArribas!$G$1:$G$3955,[1]ReportePolizaPorFiltroArribas!$O$1:$O$3955,"No Encontrado",0) -> 2025-10 | D28: =_xlfn.XLOOKUP(B28,[2]Tablero!$AP$1:$AP$6608,[2]Tablero!$AE$1:$AE$6608,"No Encontrado",0) -> 03 - PENDIENTE | E28: 6. Revisar renovación | F28: =IF(E28<>"",_xlfn.XLOOKUP(G28,pivot!$B$1:$B$34,pivot!$A$1:$A$34,"",0),"") -> Jesus | G28: FORMACION LABORAL | H28: 2025-09-25 | M28: =IF(C28<=TEXT(H28,"YYYY-MM"),2,6) -> 6
A29: URRUTIA NUÑEZ PAOLA PILAR | B29: 1469526 | C29: =_xlfn.XLOOKUP(B29,[1]ReportePolizaPorFiltroArribas!$G$1:$G$3955,[1]ReportePolizaPorFiltroArribas!$O$1:$O$3955,"No Encontrado",0) -> 2025-11 | D29: =_xlfn.XLOOKUP(B29,[2]Tablero!$AP$1:$AP$6608,[2]Tablero!$AE$1:$AE$6608,"No Encontrado",0) -> No Encontrado | E29: 6. Revisar renovación | F29: =IF(E29<>"",_xlfn.XLOOKUP(G29,pivot!$B$1:$B$34,pivot!$A$1:$A$34,"",0),"") -> Cesar | G29: WEB VEHICULOS | H29: 2025-09-18 | M29: =IF(C29<=TEXT(H29,"YYYY-MM"),2,6) -> 6
A30: ISLA HERRERA HARRY | B30: 1469534 | C30: =_xlfn.XLOOKUP(B30,[1]ReportePolizaPorFiltroArribas!$G$1:$G$3955,[1]ReportePolizaPorFiltroArribas!$O$1:$O$3955,"No Encontrado",0) -> 2025-11 | D30: =_xlfn.XLOOKUP(B30,[2]Tablero!$AP$1:$AP$6608,[2]Tablero!$AE$1:$AE$6608,"No Encontrado",0) -> 03 - PENDIENTE | E30: 6. Revisar renovación | F30: =IF(E30<>"",_xlfn.XLOOKUP(G30,pivot!$B$1:$B$34,pivot!$A$1:$A$34,"",0),"") -> Cesar | G30: WEB VEHICULOS | H30: 2025-10-11 | M30: =IF(C30<=TEXT(H30,"YYYY-MM"),2,6) -> 6
A31: AGUAS DE BAYOVAR S.A.C. | B31: 251980 | C31: =_xlfn.XLOOKUP(B31,[1]ReportePolizaPorFiltroArribas!$G$1:$G$3955,[1]ReportePolizaPorFiltroArribas!$O$1:$O$3955,"No Encontrado",0) -> 2025-11 | D31: =_xlfn.XLOOKUP(B31,[2]Tablero!$AP$1:$AP$6608,[2]Tablero!$AE$1:$AE$6608,"No Encontrado",0) -> 01 - RENOVADA | F31: =IF(E31<>"",_xlfn.XLOOKUP(G31,pivot!$B$1:$B$34,pivot!$A$1:$A$34,"",0),"") | G31: VIDA LEY D.L. 688 | H31: 2025-11-01 | M31: =IF(C31<=TEXT(H31,"YYYY-MM"),2,6) -> 2
A32: TALLERES LA LEGUA SOCIEDAD ANONIMA CERRADA - TALLERES LA LEGUA S.A.C. | B32: 93965515 | C32: =_xlfn.XLOOKUP(B32,[1]ReportePolizaPorFiltroArribas!$G$1:$G$3955,[1]ReportePolizaPorFiltroArribas!$O$1:$O$3955,"No Encontrado",0) -> 2025-11 | D32: =_xlfn.XLOOKUP(B32,[2]Tablero!$AP$1:$AP$6608,[2]Tablero!$AE$1:$AE$6608,"No Encontrado",0) -> 03 - PENDIENTE | F32: =IF(E32<>"",_xlfn.XLOOKUP(G32,pivot!$B$1:$B$34,pivot!$A$1:$A$34,"",0),"") | G32: VIDA LEY D.L. 688 | H32: 2025-11-01 | M32: =IF(C32<=TEXT(H32,"YYYY-MM"),2,6) -> 2
A33: CLUB SPORTING CRISTAL S.A. | B33: E0002259 | C33: =_xlfn.XLOOKUP(B33,[1]ReportePolizaPorFiltroArribas!$G$1:$G$3955,[1]ReportePolizaPorFiltroArribas!$O$1:$O$3955,"No Encontrado",0) -> No Encontrado | D33: =_xlfn.XLOOKUP(B33,[2]Tablero!$AP$1:$AP$6608,[2]Tablero!$AE$1:$AE$6608,"No Encontrado",0) -> 05 - ANULADA EN VIGENCIA | F33: =IF(E33<>"",_xlfn.XLOOKUP(G33,pivot!$B$1:$B$34,pivot!$A$1:$A$34,"",0),"") | G33: EPS | H33: 2023-05-29 | M33: =IF(C33<=TEXT(H33,"YYYY-MM"),2,6) -> 6
A34: CAMPARI PERU SOCIEDAD ANONIMA CERRADA - CAMPARI PERU S.A.C. | B34: E0029631 | C34: =_xlfn.XLOOKUP(B34,[1]ReportePolizaPorFiltroArribas!$G$1:$G$3955,[1]ReportePolizaPorFiltroArribas!$O$1:$O$3955,"No Encontrado",0) -> No Encontrado | D34: =_xlfn.XLOOKUP(B34,[2]Tablero!$AP$1:$AP$6608,[2]Tablero!$AE$1:$AE$6608,"No Encontrado",0) -> 04 - NO RENOVADA | F34: =IF(E34<>"",_xlfn.XLOOKUP(G34,pivot!$B$1:$B$34,pivot!$A$1:$A$34,"",0),"") | G34: EPS | H34: 2023-10-02 | M34: =IF(C34<=TEXT(H34,"YYYY-MM"),2,6) -> 6
A35: CIMER INGENIEROS SAC | B35: S0350529 | C35: =_xlfn.XLOOKUP(B35,[1]ReportePolizaPorFiltroArribas!$G$1:$G$3955,[1]ReportePolizaPorFiltroArribas!$O$1:$O$3955,"No Encontrado",0) -> No Encontrado | D35: =_xlfn.XLOOKUP(B35,[2]Tablero!$AP$1:$AP$6608,[2]Tablero!$AE$1:$AE$6608,"No Encontrado",0) -> 04 - NO RENOVADA | F35: =IF(E35<>"",_xlfn.XLOOKUP(G35,pivot!$B$1:$B$34,pivot!$A$1:$A$34,"",0),"") | G35: S.C.T.R. - SALUD | H35: 2024-12-02 | M35: =IF(C35<=TEXT(H35,"YYYY-MM"),2,6) -> 6
A36: DIGITAL BUSINESS PERU S.A.C. | B36: E0004449 | C36: =_xlfn.XLOOKUP(B36,[1]ReportePolizaPorFiltroArribas!$G$1:$G$3955,[1]ReportePolizaPorFiltroArribas!$O$1:$O$3955,"No Encontrado",0) -> No Encontrado | D36: =_xlfn.XLOOKUP(B36,[2]Tablero!$AP$1:$AP$6608,[2]Tablero!$AE$1:$AE$6608,"No Encontrado",0) -> 05 - ANULADA EN VIGENCIA | F36: =IF(E36<>"",_xlfn.XLOOKUP(G36,pivot!$B$1:$B$34,pivot!$A$1:$A$34,"",0),"") | G36: EPS | H36: 2025-02-03 | M36: =IF(C36<=TEXT(H36,"YYYY-MM"),2,6) -> 6
A37: BELTRAN BYRNE GUILLERMO | B37: E0027232 | C37: =_xlfn.XLOOKUP(B37,[1]ReportePolizaPorFiltroArribas!$G$1:$G$3955,[1]ReportePolizaPorFiltroArribas!$O$1:$O$3955,"No Encontrado",0) -> No Encontrado | D37: =_xlfn.XLOOKUP(B37,[2]Tablero!$AP$1:$AP$6608,[2]Tablero!$AE$1:$AE$6608,"No Encontrado",0) -> 05 - ANULADA EN VIGENCIA | F37: =IF(E37<>"",_xlfn.XLOOKUP(G37,pivot!$B$1:$B$34,pivot!$A$1:$A$34,"",0),"") | G37: EPS | H37: 2025-05-07 | M37: =IF(C37<=TEXT(H37,"YYYY-MM"),2,6) -> 6
A38: CONTRERAS IVARCENA EDUARDO DIEGO | B38: 1483595 | C38: =_xlfn.XLOOKUP(B38,[1]ReportePolizaPorFiltroArribas!$G$1:$G$3955,[1]ReportePolizaPorFiltroArribas!$O$1:$O$3955,"No Encontrado",0) -> 2026-01 | D38: =_xlfn.XLOOKUP(B38,[2]Tablero!$AP$1:$AP$6608,[2]Tablero!$AE$1:$AE$6608,"No Encontrado",0) -> 01 - RENOVADA | F38: =IF(E38<>"",_xlfn.XLOOKUP(G38,pivot!$B$1:$B$34,pivot!$A$1:$A$34,"",0),"") | G38: WEB VEHICULOS | H38: 2025-05-28 | M38: =IF(C38<=TEXT(H38,"YYYY-MM"),2,6) -> 6
A39: BRAVO GARCIA BELEN SARAI | B39: 67765 | C39: =_xlfn.XLOOKUP(B39,[1]ReportePolizaPorFiltroArribas!$G$1:$G$3955,[1]ReportePolizaPorFiltroArribas!$O$1:$O$3955,"No Encontrado",0) -> 2026-01 | D39: =_xlfn.XLOOKUP(B39,[2]Tablero!$AP$1:$AP$6608,[2]Tablero!$AE$1:$AE$6608,"No Encontrado",0) -> 01 - RENOVADA | F39: =IF(E39<>"",_xlfn.XLOOKUP(G39,pivot!$B$1:$B$34,pivot!$A$1:$A$34,"",0),"") | G39: SALUD RED PREFERENTE | H39: 2025-07-28 | M39: =IF(C39<=TEXT(H39,"YYYY-MM"),2,6) -> 6
A40: INMOBILIARIA EGP S.A.C. | B40: 1544218 | C40: =_xlfn.XLOOKUP(B40,[1]ReportePolizaPorFiltroArribas!$G$1:$G$3955,[1]ReportePolizaPorFiltroArribas!$O$1:$O$3955,"No Encontrado",0) -> 2026-04 | D40: =_xlfn.XLOOKUP(B40,[2]Tablero!$AP$1:$AP$6608,[2]Tablero!$AE$1:$AE$6608,"No Encontrado",0) -> 01 - RENOVADA | F40: =IF(E40<>"",_xlfn.XLOOKUP(G40,pivot!$B$1:$B$34,pivot!$A$1:$A$34,"",0),"") | G40: WEB VEHICULOS | H40: 2025-07-29 | M40: =IF(C40<=TEXT(H40,"YYYY-MM"),2,6) -> 6
A41: TEGA INDUSTRIES PERU S.A.C. | B41: 48599 | C41: =_xlfn.XLOOKUP(B41,[1]ReportePolizaPorFiltroArribas!$G$1:$G$3955,[1]ReportePolizaPorFiltroArribas!$O$1:$O$3955,"No Encontrado",0) -> 2026-03 | D41: =_xlfn.XLOOKUP(B41,[2]Tablero!$AP$1:$AP$6608,[2]Tablero!$AE$1:$AE$6608,"No Encontrado",0) -> 03 - PENDIENTE | F41: =IF(E41<>"",_xlfn.XLOOKUP(G41,pivot!$B$1:$B$34,pivot!$A$1:$A$34,"",0),"") | G41: FORMACION LABORAL | H41: 2025-07-31 | M41: =IF(C41<=TEXT(H41,"YYYY-MM"),2,6) -> 6
A42: DIGITAL BUSINESS PERU S.A.C. | B42: 67289811 | C42: =_xlfn.XLOOKUP(B42,[1]ReportePolizaPorFiltroArribas!$G$1:$G$3955,[1]ReportePolizaPorFiltroArribas!$O$1:$O$3955,"No Encontrado",0) -> 2026-03 | D42: =_xlfn.XLOOKUP(B42,[2]Tablero!$AP$1:$AP$6608,[2]Tablero!$AE$1:$AE$6608,"No Encontrado",0) -> 05 - ANULADA EN VIGENCIA | F42: =IF(E42<>"",_xlfn.XLOOKUP(G42,pivot!$B$1:$B$34,pivot!$A$1:$A$34,"",0),"") | G42: VIDA LEY D.L. 688 | H42: 2025-08-01 | M42: =IF(C42<=TEXT(H42,"YYYY-MM"),2,6) -> 6
A43: VARAS RUIZ LUCIA MIREILLE | B43: E0035204 | C43: =_xlfn.XLOOKUP(B43,[1]ReportePolizaPorFiltroArribas!$G$1:$G$3955,[1]ReportePolizaPorFiltroArribas!$O$1:$O$3955,"No Encontrado",0) -> No Encontrado | D43: =_xlfn.XLOOKUP(B43,[2]Tablero!$AP$1:$AP$6608,[2]Tablero!$AE$1:$AE$6608,"No Encontrado",0) -> 04 - NO RENOVADA | F43: =IF(E43<>"",_xlfn.XLOOKUP(G43,pivot!$B$1:$B$34,pivot!$A$1:$A$34,"",0),"") | G43: EPS | H43: 2025-08-14 | M43: =IF(C43<=TEXT(H43,"YYYY-MM"),2,6) -> 6
A44: DIGITAL VENTURES S.A.C. | B44: 1300364536 | C44: =_xlfn.XLOOKUP(B44,[1]ReportePolizaPorFiltroArribas!$G$1:$G$3955,[1]ReportePolizaPorFiltroArribas!$O$1:$O$3955,"No Encontrado",0) -> 2025-12 | D44: =_xlfn.XLOOKUP(B44,[2]Tablero!$AP$1:$AP$6608,[2]Tablero!$AE$1:$AE$6608,"No Encontrado",0) -> 01 - RENOVADA | F44: =IF(E44<>"",_xlfn.XLOOKUP(G44,pivot!$B$1:$B$34,pivot!$A$1:$A$34,"",0),"") | G44: VIDA LEY D.L. 688 | H44: 2025-08-23 | M44: =IF(C44<=TEXT(H44,"YYYY-MM"),2,6) -> 6
A45: GONZALES SALAZAR JUAN MANUEL | B45: 1443523 | C45: =_xlfn.XLOOKUP(B45,[1]ReportePolizaPorFiltroArribas!$G$1:$G$3955,[1]ReportePolizaPorFiltroArribas!$O$1:$O$3955,"No Encontrado",0) -> 2026-07 | D45: =_xlfn.XLOOKUP(B45,[2]Tablero!$AP$1:$AP$6608,[2]Tablero!$AE$1:$AE$6608,"No Encontrado",0) -> 01 - RENOVADA | F45: =IF(E45<>"",_xlfn.XLOOKUP(G45,pivot!$B$1:$B$34,pivot!$A$1:$A$34,"",0),"") | G45: WEB VEHICULOS | H45: 2025-08-25 | M45: =IF(C45<=TEXT(H45,"YYYY-MM"),2,6) -> 6
A46: GESTION A1 S.A.C. - GA1 S.A.C. | B46: E0033183 | C46: =_xlfn.XLOOKUP(B46,[1]ReportePolizaPorFiltroArribas!$G$1:$G$3955,[1]ReportePolizaPorFiltroArribas!$O$1:$O$3955,"No Encontrado",0) -> 2025-12 | D46: =_xlfn.XLOOKUP(B46,[2]Tablero!$AP$1:$AP$6608,[2]Tablero!$AE$1:$AE$6608,"No Encontrado",0) -> 03 - PENDIENTE | F46: =IF(E46<>"",_xlfn.XLOOKUP(G46,pivot!$B$1:$B$34,pivot!$A$1:$A$34,"",0),"") | G46: EPS | H46: 2025-09-01 | M46: =IF(C46<=TEXT(H46,"YYYY-MM"),2,6) -> 6
A47: XIAOMI TECHNOLOGIES PERU S.A.C. | B47: 54590 | C47: =_xlfn.XLOOKUP(B47,[1]ReportePolizaPorFiltroArribas!$G$1:$G$3955,[1]ReportePolizaPorFiltroArribas!$O$1:$O$3955,"No Encontrado",0) -> 2026-09 | D47: =_xlfn.XLOOKUP(B47,[2]Tablero!$AP$1:$AP$6608,[2]Tablero!$AE$1:$AE$6608,"No Encontrado",0) -> 03 - PENDIENTE | F47: =IF(E47<>"",_xlfn.XLOOKUP(G47,pivot!$B$1:$B$34,pivot!$A$1:$A$34,"",0),"") | G47: FULLSALUD | H47: 2025-09-04 | M47: =IF(C47<=TEXT(H47,"YYYY-MM"),2,6) -> 6
A48: XIAOMI RETAIL PERU S.A.C. | B48: 54605 | C48: =_xlfn.XLOOKUP(B48,[1]ReportePolizaPorFiltroArribas!$G$1:$G$3955,[1]ReportePolizaPorFiltroArribas!$O$1:$O$3955,"No Encontrado",0) -> 2026-09 | D48: =_xlfn.XLOOKUP(B48,[2]Tablero!$AP$1:$AP$6608,[2]Tablero!$AE$1:$AE$6608,"No Encontrado",0) -> 03 - PENDIENTE | F48: =IF(E48<>"",_xlfn.XLOOKUP(G48,pivot!$B$1:$B$34,pivot!$A$1:$A$34,"",0),"") | G48: FULLSALUD | H48: 2025-09-04 | M48: =IF(C48<=TEXT(H48,"YYYY-MM"),2,6) -> 6
A49: VALEI PRODUCCIONES E.I.R.L | B49: 69523 | C49: =_xlfn.XLOOKUP(B49,[1]ReportePolizaPorFiltroArribas!$G$1:$G$3955,[1]ReportePolizaPorFiltroArribas!$O$1:$O$3955,"No Encontrado",0) -> 2026-02 | D49: =_xlfn.XLOOKUP(B49,[2]Tablero!$AP$1:$AP$6608,[2]Tablero!$AE$1:$AE$6608,"No Encontrado",0) -> 01 - RENOVADA | F49: =IF(E49<>"",_xlfn.XLOOKUP(G49,pivot!$B$1:$B$34,pivot!$A$1:$A$34,"",0),"") | G49: SALUD RED MÉDICA | H49: 2025-09-04 | M49: =IF(C49<=TEXT(H49,"YYYY-MM"),2,6) -> 6
A50: UREÑA YEPEZ JENNY MARIA | B50: 70152 | C50: =_xlfn.XLOOKUP(B50,[1]ReportePolizaPorFiltroArribas!$G$1:$G$3955,[1]ReportePolizaPorFiltroArribas!$O$1:$O$3955,"No Encontrado",0) -> 2026-04 | D50: =_xlfn.XLOOKUP(B50,[2]Tablero!$AP$1:$AP$6608,[2]Tablero!$AE$1:$AE$6608,"No Encontrado",0) -> 01 - RENOVADA | F50: =IF(E50<>"",_xlfn.XLOOKUP(G50,pivot!$B$1:$B$34,pivot!$A$1:$A$34,"",0),"") | G50: SALUD RED MÉDICA | H50: 2025-09-04 | M50: =IF(C50<=TEXT(H50,"YYYY-MM"),2,6) -> 6
A51: UREÑA YEPEZ JENNY MARIA | B51: 50846 | C51: =_xlfn.XLOOKUP(B51,[1]ReportePolizaPorFiltroArribas!$G$1:$G$3955,[1]ReportePolizaPorFiltroArribas!$O$1:$O$3955,"No Encontrado",0) -> 2026-09 | D51: =_xlfn.XLOOKUP(B51,[2]Tablero!$AP$1:$AP$6608,[2]Tablero!$AE$1:$AE$6608,"No Encontrado",0) -> 01 - RENOVADA | F51: =IF(E51<>"",_xlfn.XLOOKUP(G51,pivot!$B$1:$B$34,pivot!$A$1:$A$34,"",0),"") | G51: FULLSALUD | H51: 2025-09-06 | M51: =IF(C51<=TEXT(H51,"YYYY-MM"),2,6) -> 6
A52: ARBULU SECLEN EDUARDO ALFREDO | B52: 102050 | C52: =_xlfn.XLOOKUP(B52,[1]ReportePolizaPorFiltroArribas!$G$1:$G$3955,[1]ReportePolizaPorFiltroArribas!$O$1:$O$3955,"No Encontrado",0) -> 2026-02 | D52: =_xlfn.XLOOKUP(B52,[2]Tablero!$AP$1:$AP$6608,[2]Tablero!$AE$1:$AE$6608,"No Encontrado",0) -> 01 - RENOVADA | F52: =IF(E52<>"",_xlfn.XLOOKUP(G52,pivot!$B$1:$B$34,pivot!$A$1:$A$34,"",0),"") | G52: SALUD RED MÉDICA | H52: 2025-09-10 | M52: =IF(C52<=TEXT(H52,"YYYY-MM"),2,6) -> 6
A53: CALLE LOS JARDINES NUMERO 109-117 URBANIZACIÓN CLUB GOLF LOS INCAS SANTIAGO DE SURCO | B53: 1300620053 | C53: =_xlfn.XLOOKUP(B53,[1]ReportePolizaPorFiltroArribas!$G$1:$G$3955,[1]ReportePolizaPorFiltroArribas!$O$1:$O$3955,"No Encontrado",0) -> 2026-07 | D53: =_xlfn.XLOOKUP(B53,[2]Tablero!$AP$1:$AP$6608,[2]Tablero!$AE$1:$AE$6608,"No Encontrado",0) -> 01 - RENOVADA | F53: =IF(E53<>"",_xlfn.XLOOKUP(G53,pivot!$B$1:$B$34,pivot!$A$1:$A$34,"",0),"") | G53: VIDA LEY D.L. 688 | H53: 2025-09-11 | M53: =IF(C53<=TEXT(H53,"YYYY-MM"),2,6) -> 6
A54: CELI MORALES DANIEL ALEXIS | B54: 768638 | C54: =_xlfn.XLOOKUP(B54,[1]ReportePolizaPorFiltroArribas!$G$1:$G$3955,[1]ReportePolizaPorFiltroArribas!$O$1:$O$3955,"No Encontrado",0) -> 2026-06 | D54: =_xlfn.XLOOKUP(B54,[2]Tablero!$AP$1:$AP$6608,[2]Tablero!$AE$1:$AE$6608,"No Encontrado",0) -> 01 - RENOVADA | F54: =IF(E54<>"",_xlfn.XLOOKUP(G54,pivot!$B$1:$B$34,pivot!$A$1:$A$34,"",0),"") | G54: WEB VEHICULOS | H54: 2025-09-12 | M54: =IF(C54<=TEXT(H54,"YYYY-MM"),2,6) -> 6
A55: ESPINOSA SAYAN MARIA DEL ROSARIO | B55: 1532759 | C55: =_xlfn.XLOOKUP(B55,[1]ReportePolizaPorFiltroArribas!$G$1:$G$3955,[1]ReportePolizaPorFiltroArribas!$O$1:$O$3955,"No Encontrado",0) -> 2026-06 | D55: =_xlfn.XLOOKUP(B55,[2]Tablero!$AP$1:$AP$6608,[2]Tablero!$AE$1:$AE$6608,"No Encontrado",0) -> 01 - RENOVADA | F55: =IF(E55<>"",_xlfn.XLOOKUP(G55,pivot!$B$1:$B$34,pivot!$A$1:$A$34,"",0),"") | G55: WEB VEHICULOS | H55: 2025-09-12 | M55: =IF(C55<=TEXT(H55,"YYYY-MM"),2,6) -> 6
A56: VALVERDE VALVERDE ALEXANDER GUILLERMO | B56: 5258 | C56: =_xlfn.XLOOKUP(B56,[1]ReportePolizaPorFiltroArribas!$G$1:$G$3955,[1]ReportePolizaPorFiltroArribas!$O$1:$O$3955,"No Encontrado",0) -> 2026-08 | D56: =_xlfn.XLOOKUP(B56,[2]Tablero!$AP$1:$AP$6608,[2]Tablero!$AE$1:$AE$6608,"No Encontrado",0) -> 01 - RENOVADA | F56: =IF(E56<>"",_xlfn.XLOOKUP(G56,pivot!$B$1:$B$34,pivot!$A$1:$A$34,"",0),"") | G56: ONCO. INTEGRAL INDIVIDUAL BROKERS | H56: 2025-09-14 | M56: =IF(C56<=TEXT(H56,"YYYY-MM"),2,6) -> 6
A57: ANGELES PASCO ENZO ANDRE | B57: E0034069 | C57: =_xlfn.XLOOKUP(B57,[1]ReportePolizaPorFiltroArribas!$G$1:$G$3955,[1]ReportePolizaPorFiltroArribas!$O$1:$O$3955,"No Encontrado",0) -> 2026-04 | D57: =_xlfn.XLOOKUP(B57,[2]Tablero!$AP$1:$AP$6608,[2]Tablero!$AE$1:$AE$6608,"No Encontrado",0) -> 01 - RENOVADA | F57: =IF(E57<>"",_xlfn.XLOOKUP(G57,pivot!$B$1:$B$34,pivot!$A$1:$A$34,"",0),"") | G57: EPS | H57: 2025-09-15 | M57: =IF(C57<=TEXT(H57,"YYYY-MM"),2,6) -> 6
A58: LLONA GARCIA MIRO PABLO EMILIO | B58: 1512436 | C58: =_xlfn.XLOOKUP(B58,[1]ReportePolizaPorFiltroArribas!$G$1:$G$3955,[1]ReportePolizaPorFiltroArribas!$O$1:$O$3955,"No Encontrado",0) -> 2026-04 | D58: =_xlfn.XLOOKUP(B58,[2]Tablero!$AP$1:$AP$6608,[2]Tablero!$AE$1:$AE$6608,"No Encontrado",0) -> 01 - RENOVADA | F58: =IF(E58<>"",_xlfn.XLOOKUP(G58,pivot!$B$1:$B$34,pivot!$A$1:$A$34,"",0),"") | G58: WEB VEHICULOS | H58: 2025-09-17 | M58: =IF(C58<=TEXT(H58,"YYYY-MM"),2,6) -> 6
A59: XIAOMI TECHNOLOGIES PERU S.A.C. | B59: 54624 | C59: =_xlfn.XLOOKUP(B59,[1]ReportePolizaPorFiltroArribas!$G$1:$G$3955,[1]ReportePolizaPorFiltroArribas!$O$1:$O$3955,"No Encontrado",0) -> 2026-09 | D59: =_xlfn.XLOOKUP(B59,[2]Tablero!$AP$1:$AP$6608,[2]Tablero!$AE$1:$AE$6608,"No Encontrado",0) -> No Encontrado | F59: =IF(E59<>"",_xlfn.XLOOKUP(G59,pivot!$B$1:$B$34,pivot!$A$1:$A$34,"",0),"") | G59: FULLSALUD | H59: 2025-09-18 | M59: =IF(C59<=TEXT(H59,"YYYY-MM"),2,6) -> 6
A60: CONSORCIO EJECUTOR CHANCHAMAYO II | B60: 1300173825 | C60: =_xlfn.XLOOKUP(B60,[1]ReportePolizaPorFiltroArribas!$G$1:$G$3955,[1]ReportePolizaPorFiltroArribas!$O$1:$O$3955,"No Encontrado",0) -> 2025-11 | D60: =_xlfn.XLOOKUP(B60,[2]Tablero!$AP$1:$AP$6608,[2]Tablero!$AE$1:$AE$6608,"No Encontrado",0) -> No Encontrado | F60: =IF(E60<>"",_xlfn.XLOOKUP(G60,pivot!$B$1:$B$34,pivot!$A$1:$A$34,"",0),"") | G60: VIDA LEY D.L. 688 | H60: 2025-11-01 | M60: =IF(C60<=TEXT(H60,"YYYY-MM"),2,6) -> 2
A61: DIGITAL VENTURES S.A.C. | B61: E0038653 | C61: =_xlfn.XLOOKUP(B61,[1]ReportePolizaPorFiltroArribas!$G$1:$G$3955,[1]ReportePolizaPorFiltroArribas!$O$1:$O$3955,"No Encontrado",0) -> 2026-08 | D61: =_xlfn.XLOOKUP(B61,[2]Tablero!$AP$1:$AP$6608,[2]Tablero!$AE$1:$AE$6608,"No Encontrado",0) -> 01 - RENOVADA | F61: =IF(E61<>"",_xlfn.XLOOKUP(G61,pivot!$B$1:$B$34,pivot!$A$1:$A$34,"",0),"") | G61: EPS | H61: 2025-09-22 | M61: =IF(C61<=TEXT(H61,"YYYY-MM"),2,6) -> 6
A62: ESPINOZA CANAL PABLO SANTIAGO | B62: 36051 | C62: =_xlfn.XLOOKUP(B62,[1]ReportePolizaPorFiltroArribas!$G$1:$G$3955,[1]ReportePolizaPorFiltroArribas!$O$1:$O$3955,"No Encontrado",0) -> 2026-06 | D62: =_xlfn.XLOOKUP(B62,[2]Tablero!$AP$1:$AP$6608,[2]Tablero!$AE$1:$AE$6608,"No Encontrado",0) -> 01 - RENOVADA | F62: =IF(E62<>"",_xlfn.XLOOKUP(G62,pivot!$B$1:$B$34,pivot!$A$1:$A$34,"",0),"") | G62: SALUD RED PREFERENTE | H62: 2025-09-25 | M62: =IF(C62<=TEXT(H62,"YYYY-MM"),2,6) -> 6
A63: SEMINARIO Y CIA S.A.B. S. A. | B63: 44936820 | C63: =_xlfn.XLOOKUP(B63,[1]ReportePolizaPorFiltroArribas!$G$1:$G$3955,[1]ReportePolizaPorFiltroArribas!$O$1:$O$3955,"No Encontrado",0) -> 2026-06 | D63: =_xlfn.XLOOKUP(B63,[2]Tablero!$AP$1:$AP$6608,[2]Tablero!$AE$1:$AE$6608,"No Encontrado",0) -> 03 - PENDIENTE | F63: =IF(E63<>"",_xlfn.XLOOKUP(G63,pivot!$B$1:$B$34,pivot!$A$1:$A$34,"",0),"") | G63: VIDA LEY 2DA CAPA | H63: 2025-09-26 | M63: =IF(C63<=TEXT(H63,"YYYY-MM"),2,6) -> 6
A64: BENDEZU MESCUA MELISSA | B64: 39658 | C64: =_xlfn.XLOOKUP(B64,[1]ReportePolizaPorFiltroArribas!$G$1:$G$3955,[1]ReportePolizaPorFiltroArribas!$O$1:$O$3955,"No Encontrado",0) -> 2026-02 | D64: =_xlfn.XLOOKUP(B64,[2]Tablero!$AP$1:$AP$6608,[2]Tablero!$AE$1:$AE$6608,"No Encontrado",0) -> 01 - RENOVADA | F64: =IF(E64<>"",_xlfn.XLOOKUP(G64,pivot!$B$1:$B$34,pivot!$A$1:$A$34,"",0),"") | G64: SALUD RED PREFERENTE | H64: 2025-09-27 | M64: =IF(C64<=TEXT(H64,"YYYY-MM"),2,6) -> 6
A65: BUSINESS ANALYTICS S.A.C. | B65: 1300376784 | C65: =_xlfn.XLOOKUP(B65,[1]ReportePolizaPorFiltroArribas!$G$1:$G$3955,[1]ReportePolizaPorFiltroArribas!$O$1:$O$3955,"No Encontrado",0) -> 2025-12 | D65: =_xlfn.XLOOKUP(B65,[2]Tablero!$AP$1:$AP$6608,[2]Tablero!$AE$1:$AE$6608,"No Encontrado",0) -> 01 - RENOVADA | F65: =IF(E65<>"",_xlfn.XLOOKUP(G65,pivot!$B$1:$B$34,pivot!$A$1:$A$34,"",0),"") | G65: VIDA LEY D.L. 688 | H65: 2025-09-28 | M65: =IF(C65<=TEXT(H65,"YYYY-MM"),2,6) -> 6
A66: SOCIEDAD AGRICOLA YOLANDA PATRICIA S.A.C. | B66: 94445894 | C66: =_xlfn.XLOOKUP(B66,[1]ReportePolizaPorFiltroArribas!$G$1:$G$3955,[1]ReportePolizaPorFiltroArribas!$O$1:$O$3955,"No Encontrado",0) -> 2025-11 | D66: =_xlfn.XLOOKUP(B66,[2]Tablero!$AP$1:$AP$6608,[2]Tablero!$AE$1:$AE$6608,"No Encontrado",0) -> 03 - PENDIENTE | F66: =IF(E66<>"",_xlfn.XLOOKUP(G66,pivot!$B$1:$B$34,pivot!$A$1:$A$34,"",0),"") | G66: VIDA LEY D.L. 688 | H66: 2025-11-02 | M66: =IF(C66<=TEXT(H66,"YYYY-MM"),2,6) -> 2
A67: ACRES SOCIEDAD ADMINISTRADORA DE FONDOS DE INVERSION S.A. - ACRES SAFI S.A. | B67: E0028123 | C67: =_xlfn.XLOOKUP(B67,[1]ReportePolizaPorFiltroArribas!$G$1:$G$3955,[1]ReportePolizaPorFiltroArribas!$O$1:$O$3955,"No Encontrado",0) -> 2026-04 | D67: =_xlfn.XLOOKUP(B67,[2]Tablero!$AP$1:$AP$6608,[2]Tablero!$AE$1:$AE$6608,"No Encontrado",0) -> 01 - RENOVADA | F67: =IF(E67<>"",_xlfn.XLOOKUP(G67,pivot!$B$1:$B$34,pivot!$A$1:$A$34,"",0),"") | G67: EPS | H67: 2025-10-01 | M67: =IF(C67<=TEXT(H67,"YYYY-MM"),2,6) -> 6
A68: ACRES SOCIEDAD AGENTE DE BOLSA S.A. | B68: E0022240 | C68: =_xlfn.XLOOKUP(B68,[1]ReportePolizaPorFiltroArribas!$G$1:$G$3955,[1]ReportePolizaPorFiltroArribas!$O$1:$O$3955,"No Encontrado",0) -> 2026-04 | D68: =_xlfn.XLOOKUP(B68,[2]Tablero!$AP$1:$AP$6608,[2]Tablero!$AE$1:$AE$6608,"No Encontrado",0) -> 01 - RENOVADA | F68: =IF(E68<>"",_xlfn.XLOOKUP(G68,pivot!$B$1:$B$34,pivot!$A$1:$A$34,"",0),"") | G68: EPS | H68: 2025-10-01 | M68: =IF(C68<=TEXT(H68,"YYYY-MM"),2,6) -> 6
A69: INSTITUTO DE HORTICULTURA TERAPEUTICA S.A.C. | B69: E0037543 | C69: =_xlfn.XLOOKUP(B69,[1]ReportePolizaPorFiltroArribas!$G$1:$G$3955,[1]ReportePolizaPorFiltroArribas!$O$1:$O$3955,"No Encontrado",0) -> 2026-03 | D69: =_xlfn.XLOOKUP(B69,[2]Tablero!$AP$1:$AP$6608,[2]Tablero!$AE$1:$AE$6608,"No Encontrado",0) -> 01 - RENOVADA | F69: =IF(E69<>"",_xlfn.XLOOKUP(G69,pivot!$B$1:$B$34,pivot!$A$1:$A$34,"",0),"") | G69: EPS | H69: 2025-10-01 | M69: =IF(C69<=TEXT(H69,"YYYY-MM"),2,6) -> 6
A70: CONEXIS GROUP SOCIEDAD ANONIMA CERRADA | B70: E0028118 | C70: =_xlfn.XLOOKUP(B70,[1]ReportePolizaPorFiltroArribas!$G$1:$G$3955,[1]ReportePolizaPorFiltroArribas!$O$1:$O$3955,"No Encontrado",0) -> 2026-08 | D70: =_xlfn.XLOOKUP(B70,[2]Tablero!$AP$1:$AP$6608,[2]Tablero!$AE$1:$AE$6608,"No Encontrado",0) -> 01 - RENOVADA | F70: =IF(E70<>"",_xlfn.XLOOKUP(G70,pivot!$B$1:$B$34,pivot!$A$1:$A$34,"",0),"") | G70: EPS | H70: 2025-10-01 | M70: =IF(C70<=TEXT(H70,"YYYY-MM"),2,6) -> 6
A71: PATRIMONIO EN FIDEICOMISO - D. LEG. N°. 861 NO INSCRITO EN LA SMV DIRIGIDO A INVERSIONISTAS INSTIT | B71: E0035134 | C71: =_xlfn.XLOOKUP(B71,[1]ReportePolizaPorFiltroArribas!$G$1:$G$3955,[1]ReportePolizaPorFiltroArribas!$O$1:$O$3955,"No Encontrado",0) -> 2026-03 | D71: =_xlfn.XLOOKUP(B71,[2]Tablero!$AP$1:$AP$6608,[2]Tablero!$AE$1:$AE$6608,"No Encontrado",0) -> 01 - RENOVADA | F71: =IF(E71<>"",_xlfn.XLOOKUP(G71,pivot!$B$1:$B$34,pivot!$A$1:$A$34,"",0),"") | G71: EPS | H71: 2025-10-01 | M71: =IF(C71<=TEXT(H71,"YYYY-MM"),2,6) -> 6
A72: ACRES FINANCE S.A. | B72: E0004928 | C72: =_xlfn.XLOOKUP(B72,[1]ReportePolizaPorFiltroArribas!$G$1:$G$3955,[1]ReportePolizaPorFiltroArribas!$O$1:$O$3955,"No Encontrado",0) -> 2026-04 | D72: =_xlfn.XLOOKUP(B72,[2]Tablero!$AP$1:$AP$6608,[2]Tablero!$AE$1:$AE$6608,"No Encontrado",0) -> 01 - RENOVADA | F72: =IF(E72<>"",_xlfn.XLOOKUP(G72,pivot!$B$1:$B$34,pivot!$A$1:$A$34,"",0),"") | G72: EPS | H72: 2025-10-01 | M72: =IF(C72<=TEXT(H72,"YYYY-MM"),2,6) -> 6
A73: ACRES SOCIEDAD TITULIZADORA S.A. | B73: E0020911 | C73: =_xlfn.XLOOKUP(B73,[1]ReportePolizaPorFiltroArribas!$G$1:$G$3955,[1]ReportePolizaPorFiltroArribas!$O$1:$O$3955,"No Encontrado",0) -> 2026-04 | D73: =_xlfn.XLOOKUP(B73,[2]Tablero!$AP$1:$AP$6608,[2]Tablero!$AE$1:$AE$6608,"No Encontrado",0) -> 01 - RENOVADA | F73: =IF(E73<>"",_xlfn.XLOOKUP(G73,pivot!$B$1:$B$34,pivot!$A$1:$A$34,"",0),"") | G73: EPS | H73: 2025-10-01 | M73: =IF(C73<=TEXT(H73,"YYYY-MM"),2,6) -> 6
A74: AC TOURS S.A.C. | B74: E0012974 | C74: =_xlfn.XLOOKUP(B74,[1]ReportePolizaPorFiltroArribas!$G$1:$G$3955,[1]ReportePolizaPorFiltroArribas!$O$1:$O$3955,"No Encontrado",0) -> 2026-08 | D74: =_xlfn.XLOOKUP(B74,[2]Tablero!$AP$1:$AP$6608,[2]Tablero!$AE$1:$AE$6608,"No Encontrado",0) -> 01 - RENOVADA | F74: =IF(E74<>"",_xlfn.XLOOKUP(G74,pivot!$B$1:$B$34,pivot!$A$1:$A$34,"",0),"") | G74: EPS | H74: 2025-10-01 | M74: =IF(C74<=TEXT(H74,"YYYY-MM"),2,6) -> 6
A75: BUSINESS ANALYTICS S.A.C. | B75: E0030659 | C75: =_xlfn.XLOOKUP(B75,[1]ReportePolizaPorFiltroArribas!$G$1:$G$3955,[1]ReportePolizaPorFiltroArribas!$O$1:$O$3955,"No Encontrado",0) -> 2025-12 | D75: =_xlfn.XLOOKUP(B75,[2]Tablero!$AP$1:$AP$6608,[2]Tablero!$AE$1:$AE$6608,"No Encontrado",0) -> 03 - PENDIENTE | F75: =IF(E75<>"",_xlfn.XLOOKUP(G75,pivot!$B$1:$B$34,pivot!$A$1:$A$34,"",0),"") | G75: EPS | H75: 2025-10-01 | M75: =IF(C75<=TEXT(H75,"YYYY-MM"),2,6) -> 6
A76: LABORATORIO FARMACEUTICO SAN JOAQUIN-ROXFARMA SOCIEDAD ANONIMA | B76: E0020619 | C76: =_xlfn.XLOOKUP(B76,[1]ReportePolizaPorFiltroArribas!$G$1:$G$3955,[1]ReportePolizaPorFiltroArribas!$O$1:$O$3955,"No Encontrado",0) -> 2026-08 | D76: =_xlfn.XLOOKUP(B76,[2]Tablero!$AP$1:$AP$6608,[2]Tablero!$AE$1:$AE$6608,"No Encontrado",0) -> 01 - RENOVADA | F76: =IF(E76<>"",_xlfn.XLOOKUP(G76,pivot!$B$1:$B$34,pivot!$A$1:$A$34,"",0),"") | G76: EPS | H76: 2025-10-01 | M76: =IF(C76<=TEXT(H76,"YYYY-MM"),2,6) -> 6
A77: PROYECTA INGENIEROS CIVILES S.A.C. | B77: E0003294 | C77: =_xlfn.XLOOKUP(B77,[1]ReportePolizaPorFiltroArribas!$G$1:$G$3955,[1]ReportePolizaPorFiltroArribas!$O$1:$O$3955,"No Encontrado",0) -> 2026-04 | D77: =_xlfn.XLOOKUP(B77,[2]Tablero!$AP$1:$AP$6608,[2]Tablero!$AE$1:$AE$6608,"No Encontrado",0) -> 01 - RENOVADA | F77: =IF(E77<>"",_xlfn.XLOOKUP(G77,pivot!$B$1:$B$34,pivot!$A$1:$A$34,"",0),"") | G77: EPS | H77: 2025-10-01 | M77: =IF(C77<=TEXT(H77,"YYYY-MM"),2,6) -> 6
A78: MENDEZ GRIMALDI BRUNELLA CRISTINA | B78: 1488144 | C78: =_xlfn.XLOOKUP(B78,[1]ReportePolizaPorFiltroArribas!$G$1:$G$3955,[1]ReportePolizaPorFiltroArribas!$O$1:$O$3955,"No Encontrado",0) -> 2026-01 | D78: =_xlfn.XLOOKUP(B78,[2]Tablero!$AP$1:$AP$6608,[2]Tablero!$AE$1:$AE$6608,"No Encontrado",0) -> 01 - RENOVADA | F78: =IF(E78<>"",_xlfn.XLOOKUP(G78,pivot!$B$1:$B$34,pivot!$A$1:$A$34,"",0),"") | G78: WEB VEHICULOS | H78: 2025-10-01 | M78: =IF(C78<=TEXT(H78,"YYYY-MM"),2,6) -> 6
A79: PASTOR MATTA DE ACEVEDO CARMEN ROSA | B79: 4018003390 | C79: =_xlfn.XLOOKUP(B79,[1]ReportePolizaPorFiltroArribas!$G$1:$G$3955,[1]ReportePolizaPorFiltroArribas!$O$1:$O$3955,"No Encontrado",0) -> 2026-04 | D79: =_xlfn.XLOOKUP(B79,[2]Tablero!$AP$1:$AP$6608,[2]Tablero!$AE$1:$AE$6608,"No Encontrado",0) -> 01 - RENOVADA | F79: =IF(E79<>"",_xlfn.XLOOKUP(G79,pivot!$B$1:$B$34,pivot!$A$1:$A$34,"",0),"") | G79: ONCOLÓGICO RIMAC | H79: 2025-10-01 | M79: =IF(C79<=TEXT(H79,"YYYY-MM"),2,6) -> 6
A80: BORJA MEJIA EDWARD | B80: 55748 | C80: =_xlfn.XLOOKUP(B80,[1]ReportePolizaPorFiltroArribas!$G$1:$G$3955,[1]ReportePolizaPorFiltroArribas!$O$1:$O$3955,"No Encontrado",0) -> 2026-04 | D80: =_xlfn.XLOOKUP(B80,[2]Tablero!$AP$1:$AP$6608,[2]Tablero!$AE$1:$AE$6608,"No Encontrado",0) -> 01 - RENOVADA | F80: =IF(E80<>"",_xlfn.XLOOKUP(G80,pivot!$B$1:$B$34,pivot!$A$1:$A$34,"",0),"") | G80: SALUD RED MÉDICA | H80: 2025-10-01 | M80: =IF(C80<=TEXT(H80,"YYYY-MM"),2,6) -> 6
A81: ALBUJAR CAMACHO JUAN CARLOS FERNANDO | B81: 62044 | C81: =_xlfn.XLOOKUP(B81,[1]ReportePolizaPorFiltroArribas!$G$1:$G$3955,[1]ReportePolizaPorFiltroArribas!$O$1:$O$3955,"No Encontrado",0) -> No Encontrado | D81: =_xlfn.XLOOKUP(B81,[2]Tablero!$AP$1:$AP$6608,[2]Tablero!$AE$1:$AE$6608,"No Encontrado",0) -> 05 - ANULADA EN VIGENCIA | F81: =IF(E81<>"",_xlfn.XLOOKUP(G81,pivot!$B$1:$B$34,pivot!$A$1:$A$34,"",0),"") | G81: SALUD RED PREFERENTE | H81: 2025-10-01 | M81: =IF(C81<=TEXT(H81,"YYYY-MM"),2,6) -> 6
A82: ALBUJAR CAMACHO JUAN CARLOS FERNANDO | B82: 90476 | C82: =_xlfn.XLOOKUP(B82,[1]ReportePolizaPorFiltroArribas!$G$1:$G$3955,[1]ReportePolizaPorFiltroArribas!$O$1:$O$3955,"No Encontrado",0) -> No Encontrado | D82: =_xlfn.XLOOKUP(B82,[2]Tablero!$AP$1:$AP$6608,[2]Tablero!$AE$1:$AE$6608,"No Encontrado",0) -> 05 - ANULADA EN VIGENCIA | F82: =IF(E82<>"",_xlfn.XLOOKUP(G82,pivot!$B$1:$B$34,pivot!$A$1:$A$34,"",0),"") | G82: SALUD RED MÉDICA | H82: 2025-10-01 | M82: =IF(C82<=TEXT(H82,"YYYY-MM"),2,6) -> 6
A83: FLORES CALDERON VALERIA IVETTE | B83: 79146 | C83: =_xlfn.XLOOKUP(B83,[1]ReportePolizaPorFiltroArribas!$G$1:$G$3955,[1]ReportePolizaPorFiltroArribas!$O$1:$O$3955,"No Encontrado",0) -> 2026-07 | D83: =_xlfn.XLOOKUP(B83,[2]Tablero!$AP$1:$AP$6608,[2]Tablero!$AE$1:$AE$6608,"No Encontrado",0) -> 01 - RENOVADA | F83: =IF(E83<>"",_xlfn.XLOOKUP(G83,pivot!$B$1:$B$34,pivot!$A$1:$A$34,"",0),"") | G83: SALUD RED MÉDICA | H83: 2025-10-01 | M83: =IF(C83<=TEXT(H83,"YYYY-MM"),2,6) -> 6
A84: SAN MARTIN NAVEA DE MUJICA MARIA EUGENIA | B84: 67615 | C84: =_xlfn.XLOOKUP(B84,[1]ReportePolizaPorFiltroArribas!$G$1:$G$3955,[1]ReportePolizaPorFiltroArribas!$O$1:$O$3955,"No Encontrado",0) -> 2026-09 | D84: =_xlfn.XLOOKUP(B84,[2]Tablero!$AP$1:$AP$6608,[2]Tablero!$AE$1:$AE$6608,"No Encontrado",0) -> 01 - RENOVADA | F84: =IF(E84<>"",_xlfn.XLOOKUP(G84,pivot!$B$1:$B$34,pivot!$A$1:$A$34,"",0),"") | G84: SALUD RED MÉDICA | H84: 2025-10-01 | M84: =IF(C84<=TEXT(H84,"YYYY-MM"),2,6) -> 6
A85: BELTRAN BYRNE GUILLERMO | B85: 74959 | C85: =_xlfn.XLOOKUP(B85,[1]ReportePolizaPorFiltroArribas!$G$1:$G$3955,[1]ReportePolizaPorFiltroArribas!$O$1:$O$3955,"No Encontrado",0) -> 2026-07 | D85: =_xlfn.XLOOKUP(B85,[2]Tablero!$AP$1:$AP$6608,[2]Tablero!$AE$1:$AE$6608,"No Encontrado",0) -> 01 - RENOVADA | F85: =IF(E85<>"",_xlfn.XLOOKUP(G85,pivot!$B$1:$B$34,pivot!$A$1:$A$34,"",0),"") | G85: SALUD RED PREFERENTE | H85: 2025-10-01 | M85: =IF(C85<=TEXT(H85,"YYYY-MM"),2,6) -> 6
A86: PESANTES PEREZ SARA MILAGROS | B86: 45693 | C86: =_xlfn.XLOOKUP(B86,[1]ReportePolizaPorFiltroArribas!$G$1:$G$3955,[1]ReportePolizaPorFiltroArribas!$O$1:$O$3955,"No Encontrado",0) -> 2026-09 | D86: =_xlfn.XLOOKUP(B86,[2]Tablero!$AP$1:$AP$6608,[2]Tablero!$AE$1:$AE$6608,"No Encontrado",0) -> 01 - RENOVADA | F86: =IF(E86<>"",_xlfn.XLOOKUP(G86,pivot!$B$1:$B$34,pivot!$A$1:$A$34,"",0),"") | G86: SALUD RED MEDICA F F V V | H86: 2025-10-01 | M86: =IF(C86<=TEXT(H86,"YYYY-MM"),2,6) -> 6
A87: XIAOMI TECHNOLOGIES PERU S.A.C. | B87: 1300359823 | C87: =_xlfn.XLOOKUP(B87,[1]ReportePolizaPorFiltroArribas!$G$1:$G$3955,[1]ReportePolizaPorFiltroArribas!$O$1:$O$3955,"No Encontrado",0) -> No Encontrado | D87: =_xlfn.XLOOKUP(B87,[2]Tablero!$AP$1:$AP$6608,[2]Tablero!$AE$1:$AE$6608,"No Encontrado",0) -> 03 - PENDIENTE | F87: =IF(E87<>"",_xlfn.XLOOKUP(G87,pivot!$B$1:$B$34,pivot!$A$1:$A$34,"",0),"") | G87: VIDA LEY D.L. 688 | H87: 2025-10-02 | M87: =IF(C87<=TEXT(H87,"YYYY-MM"),2,6) -> 6
A88: PICKMAN SANCHEZ ENA DENISSE | B88: 1563417 | C88: =_xlfn.XLOOKUP(B88,[1]ReportePolizaPorFiltroArribas!$G$1:$G$3955,[1]ReportePolizaPorFiltroArribas!$O$1:$O$3955,"No Encontrado",0) -> 2026-09 | D88: =_xlfn.XLOOKUP(B88,[2]Tablero!$AP$1:$AP$6608,[2]Tablero!$AE$1:$AE$6608,"No Encontrado",0) -> 01 - RENOVADA | F88: =IF(E88<>"",_xlfn.XLOOKUP(G88,pivot!$B$1:$B$34,pivot!$A$1:$A$34,"",0),"") | G88: WEB VEHICULOS | H88: 2025-10-03 | M88: =IF(C88<=TEXT(H88,"YYYY-MM"),2,6) -> 6
A89: VALEI PRODUCCIONES E.I.R.L | B89: 4664 | C89: =_xlfn.XLOOKUP(B89,[1]ReportePolizaPorFiltroArribas!$G$1:$G$3955,[1]ReportePolizaPorFiltroArribas!$O$1:$O$3955,"No Encontrado",0) -> 2026-02 | D89: =_xlfn.XLOOKUP(B89,[2]Tablero!$AP$1:$AP$6608,[2]Tablero!$AE$1:$AE$6608,"No Encontrado",0) -> 01 - RENOVADA | F89: =IF(E89<>"",_xlfn.XLOOKUP(G89,pivot!$B$1:$B$34,pivot!$A$1:$A$34,"",0),"") | G89: SALUD DE ORO | H89: 2025-10-04 | M89: =IF(C89<=TEXT(H89,"YYYY-MM"),2,6) -> 6
... A108: GRAÑA SARMIENTO RAFAEL EDUARDO | B108: 1547936 | C108: =_xlfn.XLOOKUP(B108,[1]ReportePolizaPorFiltroArribas!$G$1:$G$3955,[1]ReportePolizaPorFiltroArribas!$O$1:$O$3955,"No Encontrado",0) -> 2026-08 | D108: =_xlfn.XLOOKUP(B108,[2]Tablero!$AP$1:$AP$6608,[2]Tablero!$AE$1:$AE$6608,"No Encontrado",0) -> 01 - RENOVADA | F108: =IF(E108<>"",_xlfn.XLOOKUP(G108,pivot!$B$1:$B$34,pivot!$A$1:$A$34,"",0),"") | G108: WEB VEHICULOS | H108: 2025-10-11 | M108: =IF(C108<=TEXT(H108,"YYYY-MM"),2,6) -> 6
A109: AYALA MARTINEZ SARA ESTHER | B109: E0028438 | C109: =_xlfn.XLOOKUP(B109,[1]ReportePolizaPorFiltroArribas!$G$1:$G$3955,[1]ReportePolizaPorFiltroArribas!$O$1:$O$3955,"No Encontrado",0) -> 2026-02 | D109: =_xlfn.XLOOKUP(B109,[2]Tablero!$AP$1:$AP$6608,[2]Tablero!$AE$1:$AE$6608,"No Encontrado",0) -> 01 - RENOVADA | F109: =IF(E109<>"",_xlfn.XLOOKUP(G109,pivot!$B$1:$B$34,pivot!$A$1:$A$34,"",0),"") | G109: EPS | H109: 2025-10-13 | M109: =IF(C109<=TEXT(H109,"YYYY-MM"),2,6) -> 6
A110: CUMPA EXEBIO JORGE DANIEL | B110: E0026804 | C110: =_xlfn.XLOOKUP(B110,[1]ReportePolizaPorFiltroArribas!$G$1:$G$3955,[1]ReportePolizaPorFiltroArribas!$O$1:$O$3955,"No Encontrado",0) -> 2026-02 | D110: =_xlfn.XLOOKUP(B110,[2]Tablero!$AP$1:$AP$6608,[2]Tablero!$AE$1:$AE$6608,"No Encontrado",0) -> 01 - RENOVADA | F110: =IF(E110<>"",_xlfn.XLOOKUP(G110,pivot!$B$1:$B$34,pivot!$A$1:$A$34,"",0),"") | G110: EPS | H110: 2025-10-13 | M110: =IF(C110<=TEXT(H110,"YYYY-MM"),2,6) -> 6
A111: GARNIQUE SANCHEZ DANNY IVAN | B111: 1509990 | C111: =_xlfn.XLOOKUP(B111,[1]ReportePolizaPorFiltroArribas!$G$1:$G$3955,[1]ReportePolizaPorFiltroArribas!$O$1:$O$3955,"No Encontrado",0) -> 2026-04 | D111: =_xlfn.XLOOKUP(B111,[2]Tablero!$AP$1:$AP$6608,[2]Tablero!$AE$1:$AE$6608,"No Encontrado",0) -> 01 - RENOVADA | F111: =IF(E111<>"",_xlfn.XLOOKUP(G111,pivot!$B$1:$B$34,pivot!$A$1:$A$34,"",0),"") | G111: WEB VEHICULOS | H111: 2025-10-14 | M111: =IF(C111<=TEXT(H111,"YYYY-MM"),2,6) -> 6
A112: CUADROS ANTUNEZ DE MAYOLO VICTOR CIRO JOSE | B112: 1488856 | C112: =_xlfn.XLOOKUP(B112,[1]ReportePolizaPorFiltroArribas!$G$1:$G$3955,[1]ReportePolizaPorFiltroArribas!$O$1:$O$3955,"No Encontrado",0) -> 2026-01 | D112: =_xlfn.XLOOKUP(B112,[2]Tablero!$AP$1:$AP$6608,[2]Tablero!$AE$1:$AE$6608,"No Encontrado",0) -> 01 - RENOVADA | F112: =IF(E112<>"",_xlfn.XLOOKUP(G112,pivot!$B$1:$B$34,pivot!$A$1:$A$34,"",0),"") | G112: WEB VEHICULOS | H112: 2025-10-15 | M112: =IF(C112<=TEXT(H112,"YYYY-MM"),2,6) -> 6
A113: ALCANTARA QUISPE TERESA DEL PILAR | B113: 1493794 | C113: =_xlfn.XLOOKUP(B113,[1]ReportePolizaPorFiltroArribas!$G$1:$G$3955,[1]ReportePolizaPorFiltroArribas!$O$1:$O$3955,"No Encontrado",0) -> 2026-01 | D113: =_xlfn.XLOOKUP(B113,[2]Tablero!$AP$1:$AP$6608,[2]Tablero!$AE$1:$AE$6608,"No Encontrado",0) -> 01 - RENOVADA | F113: =IF(E113<>"",_xlfn.XLOOKUP(G113,pivot!$B$1:$B$34,pivot!$A$1:$A$34,"",0),"") | G113: WEB VEHICULOS | H113: 2025-10-15 | M113: =IF(C113<=TEXT(H113,"YYYY-MM"),2,6) -> 6
A114: COOK VIZURRAGA KETTY AURORA | B114: 1416594 | C114: =_xlfn.XLOOKUP(B114,[1]ReportePolizaPorFiltroArribas!$G$1:$G$3955,[1]ReportePolizaPorFiltroArribas!$O$1:$O$3955,"No Encontrado",0) -> 2026-03 | D114: =_xlfn.XLOOKUP(B114,[2]Tablero!$AP$1:$AP$6608,[2]Tablero!$AE$1:$AE$6608,"No Encontrado",0) -> 01 - RENOVADA | F114: =IF(E114<>"",_xlfn.XLOOKUP(G114,pivot!$B$1:$B$34,pivot!$A$1:$A$34,"",0),"") | G114: WEB VEHICULOS | H114: 2025-10-15 | M114: =IF(C114<=TEXT(H114,"YYYY-MM"),2,6) -> 6
A115: YEP CHANG LILIANA DORA | B115: 1538612 | C115: =_xlfn.XLOOKUP(B115,[1]ReportePolizaPorFiltroArribas!$G$1:$G$3955,[1]ReportePolizaPorFiltroArribas!$O$1:$O$3955,"No Encontrado",0) -> 2026-07 | D115: =_xlfn.XLOOKUP(B115,[2]Tablero!$AP$1:$AP$6608,[2]Tablero!$AE$1:$AE$6608,"No Encontrado",0) -> 01 - RENOVADA | F115: =IF(E115<>"",_xlfn.XLOOKUP(G115,pivot!$B$1:$B$34,pivot!$A$1:$A$34,"",0),"") | G115: WEB VEHICULOS | H115: 2025-10-15 | M115: =IF(C115<=TEXT(H115,"YYYY-MM"),2,6) -> 6
A116: LOPEZ PROAÑO LUIS LEONCIO ISRAEL | B116: 1463498 | C116: =_xlfn.XLOOKUP(B116,[1]ReportePolizaPorFiltroArribas!$G$1:$G$3955,[1]ReportePolizaPorFiltroArribas!$O$1:$O$3955,"No Encontrado",0) -> 2026-10 | D116: =_xlfn.XLOOKUP(B116,[2]Tablero!$AP$1:$AP$6608,[2]Tablero!$AE$1:$AE$6608,"No Encontrado",0) -> 01 - RENOVADA | F116: =IF(E116<>"",_xlfn.XLOOKUP(G116,pivot!$B$1:$B$34,pivot!$A$1:$A$34,"",0),"") | G116: WEB VEHICULOS | H116: 2025-10-15 | M116: =IF(C116<=TEXT(H116,"YYYY-MM"),2,6) -> 6
A117: FLORES TABOADA DE ROJAS FIORELLA GIOVANNA | B117: 1482897 | C117: =_xlfn.XLOOKUP(B117,[1]ReportePolizaPorFiltroArribas!$G$1:$G$3955,[1]ReportePolizaPorFiltroArribas!$O$1:$O$3955,"No Encontrado",0) -> 2025-12 | D117: =_xlfn.XLOOKUP(B117,[2]Tablero!$AP$1:$AP$6608,[2]Tablero!$AE$1:$AE$6608,"No Encontrado",0) -> 03 - PENDIENTE | F117: =IF(E117<>"",_xlfn.XLOOKUP(G117,pivot!$B$1:$B$34,pivot!$A$1:$A$34,"",0),"") | G117: WEB VEHICULOS | H117: 2025-10-16 | M117: =IF(C117<=TEXT(H117,"YYYY-MM"),2,6) -> 6
A118: LEON LEIVA CLARA LUZ | B118: 1491908 | C118: =_xlfn.XLOOKUP(B118,[1]ReportePolizaPorFiltroArribas!$G$1:$G$3955,[1]ReportePolizaPorFiltroArribas!$O$1:$O$3955,"No Encontrado",0) -> 2026-02 | D118: =_xlfn.XLOOKUP(B118,[2]Tablero!$AP$1:$AP$6608,[2]Tablero!$AE$1:$AE$6608,"No Encontrado",0) -> 01 - RENOVADA | F118: =IF(E118<>"",_xlfn.XLOOKUP(G118,pivot!$B$1:$B$34,pivot!$A$1:$A$34,"",0),"") | G118: WEB VEHICULOS | H118: 2025-10-16 | M118: =IF(C118<=TEXT(H118,"YYYY-MM"),2,6) -> 6
A119: LA CRUZ VICENTE DENISSE MILAGROS | B119: 30507 | C119: =_xlfn.XLOOKUP(B119,[1]ReportePolizaPorFiltroArribas!$G$1:$G$3955,[1]ReportePolizaPorFiltroArribas!$O$1:$O$3955,"No Encontrado",0) -> 2026-03 | D119: =_xlfn.XLOOKUP(B119,[2]Tablero!$AP$1:$AP$6608,[2]Tablero!$AE$1:$AE$6608,"No Encontrado",0) -> 01 - RENOVADA | F119: =IF(E119<>"",_xlfn.XLOOKUP(G119,pivot!$B$1:$B$34,pivot!$A$1:$A$34,"",0),"") | G119: SALUD FLEXIBLE | H119: 2025-10-16 | M119: =IF(C119<=TEXT(H119,"YYYY-MM"),2,6) -> 6
A120: GONZALES VARGAS HANS MICHAEL | B120: 35522 | C120: =_xlfn.XLOOKUP(B120,[1]ReportePolizaPorFiltroArribas!$G$1:$G$3955,[1]ReportePolizaPorFiltroArribas!$O$1:$O$3955,"No Encontrado",0) -> 2026-05 | D120: =_xlfn.XLOOKUP(B120,[2]Tablero!$AP$1:$AP$6608,[2]Tablero!$AE$1:$AE$6608,"No Encontrado",0) -> 01 - RENOVADA | F120: =IF(E120<>"",_xlfn.XLOOKUP(G120,pivot!$B$1:$B$34,pivot!$A$1:$A$34,"",0),"") | G120: SALUD RED PREFERENTE | H120: 2025-10-16 | M120: =IF(C120<=TEXT(H120,"YYYY-MM"),2,6) -> 6
A121: GUERRERO RIVERA MARTHA GABRIELA | B121: 1536831 | C121: =_xlfn.XLOOKUP(B121,[1]ReportePolizaPorFiltroArribas!$G$1:$G$3955,[1]ReportePolizaPorFiltroArribas!$O$1:$O$3955,"No Encontrado",0) -> 2026-06 | D121: =_xlfn.XLOOKUP(B121,[2]Tablero!$AP$1:$AP$6608,[2]Tablero!$AE$1:$AE$6608,"No Encontrado",0) -> 01 - RENOVADA | F121: =IF(E121<>"",_xlfn.XLOOKUP(G121,pivot!$B$1:$B$34,pivot!$A$1:$A$34,"",0),"") | G121: WEB VEHICULOS | H121: 2025-10-16 | M121: =IF(C121<=TEXT(H121,"YYYY-MM"),2,6) -> 6
A122: MANCO FERNANDEZ RENZO JESUS | B122: 1484358 | C122: =_xlfn.XLOOKUP(B122,[1]ReportePolizaPorFiltroArribas!$G$1:$G$3955,[1]ReportePolizaPorFiltroArribas!$O$1:$O$3955,"No Encontrado",0) -> 2025-12 | D122: =_xlfn.XLOOKUP(B122,[2]Tablero!$AP$1:$AP$6608,[2]Tablero!$AE$1:$AE$6608,"No Encontrado",0) -> 03 - PENDIENTE | F122: =IF(E122<>"",_xlfn.XLOOKUP(G122,pivot!$B$1:$B$34,pivot!$A$1:$A$34,"",0),"") | G122: WEB VEHICULOS | H122: 2025-10-17 | M122: =IF(C122<=TEXT(H122,"YYYY-MM"),2,6) -> 6
... A147: ANDERSON BLONDET ITA MARIA ANGELICA | B147: 1563861 | C147: =_xlfn.XLOOKUP(B147,[1]ReportePolizaPorFiltroArribas!$G$1:$G$3955,[1]ReportePolizaPorFiltroArribas!$O$1:$O$3955,"No Encontrado",0) -> 2026-09 | D147: =_xlfn.XLOOKUP(B147,[2]Tablero!$AP$1:$AP$6608,[2]Tablero!$AE$1:$AE$6608,"No Encontrado",0) -> 01 - RENOVADA | F147: =IF(E147<>"",_xlfn.XLOOKUP(G147,pivot!$B$1:$B$34,pivot!$A$1:$A$34,"",0),"") | G147: WEB VEHICULOS | H147: 2025-10-20 | M147: =IF(C147<=TEXT(H147,"YYYY-MM"),2,6) -> 6
A148: TEGA INDUSTRIES PERU S.A.C. | B148: E0034025 | C148: =_xlfn.XLOOKUP(B148,[1]ReportePolizaPorFiltroArribas!$G$1:$G$3955,[1]ReportePolizaPorFiltroArribas!$O$1:$O$3955,"No Encontrado",0) -> 2026-04 | D148: =_xlfn.XLOOKUP(B148,[2]Tablero!$AP$1:$AP$6608,[2]Tablero!$AE$1:$AE$6608,"No Encontrado",0) -> 01 - RENOVADA | F148: =IF(E148<>"",_xlfn.XLOOKUP(G148,pivot!$B$1:$B$34,pivot!$A$1:$A$34,"",0),"") | G148: EPS | H148: 2025-10-20 | M148: =IF(C148<=TEXT(H148,"YYYY-MM"),2,6) -> 6
A149: CALDERON LOPEZ MIGUEL ANTONIO | B149: 9632 | C149: =_xlfn.XLOOKUP(B149,[1]ReportePolizaPorFiltroArribas!$G$1:$G$3955,[1]ReportePolizaPorFiltroArribas!$O$1:$O$3955,"No Encontrado",0) -> 2026-02 | D149: =_xlfn.XLOOKUP(B149,[2]Tablero!$AP$1:$AP$6608,[2]Tablero!$AE$1:$AE$6608,"No Encontrado",0) -> 01 - RENOVADA | F149: =IF(E149<>"",_xlfn.XLOOKUP(G149,pivot!$B$1:$B$34,pivot!$A$1:$A$34,"",0),"") | G149: SALUD DE ORO | H149: 2025-10-20 | M149: =IF(C149<=TEXT(H149,"YYYY-MM"),2,6) -> 6
A150: MEJIA SIFUENTES CARLOS ALFREDO | B150: 1491923 | C150: =_xlfn.XLOOKUP(B150,[1]ReportePolizaPorFiltroArribas!$G$1:$G$3955,[1]ReportePolizaPorFiltroArribas!$O$1:$O$3955,"No Encontrado",0) -> 2026-02 | D150: =_xlfn.XLOOKUP(B150,[2]Tablero!$AP$1:$AP$6608,[2]Tablero!$AE$1:$AE$6608,"No Encontrado",0) -> 01 - RENOVADA | F150: =IF(E150<>"",_xlfn.XLOOKUP(G150,pivot!$B$1:$B$34,pivot!$A$1:$A$34,"",0),"") | G150: WEB VEHICULOS | H150: 2025-10-20 | M150: =IF(C150<=TEXT(H150,"YYYY-MM"),2,6) -> 6
A151: CALCIOS ORGANICOS DEL PERU S.A.C. | B151: 1495169 | C151: =_xlfn.XLOOKUP(B151,[1]ReportePolizaPorFiltroArribas!$G$1:$G$3955,[1]ReportePolizaPorFiltroArribas!$O$1:$O$3955,"No Encontrado",0) -> 2026-01 | D151: =_xlfn.XLOOKUP(B151,[2]Tablero!$AP$1:$AP$6608,[2]Tablero!$AE$1:$AE$6608,"No Encontrado",0) -> 01 - RENOVADA | F151: =IF(E151<>"",_xlfn.XLOOKUP(G151,pivot!$B$1:$B$34,pivot!$A$1:$A$34,"",0),"") | G151: WEB VEHICULOS | H151: 2025-10-20 | M151: =IF(C151<=TEXT(H151,"YYYY-MM"),2,6) -> 6
...

Sheet pivot
A1: Responsable | B1: CATEGORÍA
A2: Jesus | B2: S.C.T.R. - PENSION | F2: 1. No está cargado en el SICS-Tablero
A3: Jesus | B3: VIDA LEY D.L. 688 | F3: 2. Actualizar la vigencia en el SICS | G3: SICS | H3: <= | I3: VCTO
A4: Jesus | B4: VIDALEYRE | F4: 6. Revisar renovación | G4: SICS | H4: > | I4: VCTO
A5: Briyan | B5: SALUD RED PREFERENTE
A6: Briyan | B6: SALUD RED PREFERENTE F F V V
A7: Briyan | B7: SALUD RED MEDICA F F V V
A8: Jesus | B8: S.C.T.R. - SALUD
A9: Jesus | B9: VIDA GRUPO
A10: Jesus | B10: FORMACION LABORAL
A11: Jesus | B11: VIDA LEY 2DA CAPA
A12: Jesus | B12: ONCOLÓGICO RIMAC
A13: Jesus | B13: ACCIDENTES SEGURO VIDA B
A14: Briyan | B14: SALUD DE ORO F F V V
A15: Briyan | B15: SALUD FLEXIBLE
A16: Briyan | B16: FULLSALUD
... A34: Thalia | B34: 3D
