Workbook

Sheet PagosVencidos
A1: RESPONSABLE DE PAGO | B1: NRO. POLIZA | C1: CATEGORÍA | D1: VENCIMIENTO
A2: CLUB SPORTING CRISTAL S.A. | B2: E0002259 | C2: EPS | D2: 2023-05-29
A3: CAMPARI PERU SOCIEDAD ANONIMA CERRADA - CAMPARI PERU S.A.C. | B3: E0029631 | C3: EPS | D3: 2023-10-02
A4: CIMER INGENIEROS SAC | B4: S0350529 | C4: S.C.T.R. - SALUD | D4: 2024-12-02
A5: DIGITAL BUSINESS PERU S.A.C. | B5: E0004449 | C5: EPS | D5: 2025-02-03
A6: BELTRAN BYRNE GUILLERMO | B6: E0027232 | C6: EPS | D6: 2025-05-07
A7: VARAS RUIZ LUCIA MIREILLE | B7: E0035204 | C7: EPS | D7: 2025-08-14
A8: TEGA INDUSTRIES PERU S.A.C. | B8: 48599 | C8: FORMACION LABORAL | D8: 2025-09-02
A9: XIAOMI TECHNOLOGIES PERU S.A.C. | B9: 54590 | C9: FULLSALUD | D9: 2025-09-04
A10: DIGITAL VENTURES S.A.C. | B10: E0038653 | C10: EPS | D10: 2025-09-22
A11: DIGITAL VENTURES S.A.C. | B11: 1300364536 | C11: VIDA LEY D.L. 688 | D11: 2025-09-23
A12: XIAOMI TECHNOLOGIES PERU S.A.C. | B12: 48411 | C12: FORMACION LABORAL | D12: 2025-09-25
... A435: HENN KLAUS PETER WERNER | B435: 1496943 | C435: WEB VEHICULOS | D435: 2026-02-19

Sheet Hoja1
A1: RESPONSABLE DE PAGO | B1: NRO. POLIZA | C1: CATEGORÍA | D1: VENCIMIENTO
A2: CLUB SPORTING CRISTAL S.A. | B2: E0002259 | C2: EPS | D2: =VLOOKUP(B2,PagosVencidos!$B$1:$H$1883,7,0)
A3: CAMPARI PERU SOCIEDAD ANONIMA CERRADA - CAMPARI PERU S.A.C. | B3: E0029631 | C3: EPS | D3: =VLOOKUP(B3,PagosVencidos!$B$1:$H$1883,7,0)
A4: CIMER INGENIEROS SAC | B4: S0350529 | C4: S.C.T.R. - SALUD | D4: =VLOOKUP(B4,PagosVencidos!$B$1:$H$1883,7,0)
A5: DIGITAL BUSINESS PERU S.A.C. | B5: E0004449 | C5: EPS | D5: =VLOOKUP(B5,PagosVencidos!$B$1:$H$1883,7,0)
A6: BELTRAN BYRNE GUILLERMO | B6: E0027232 | C6: EPS | D6: =VLOOKUP(B6,PagosVencidos!$B$1:$H$1883,7,0)
A7: VARAS RUIZ LUCIA MIREILLE | B7: E0035204 | C7: EPS | D7: =VLOOKUP(B7,PagosVencidos!$B$1:$H$1883,7,0)
A8: TEGA INDUSTRIES PERU S.A.C. | B8: 48599 | C8: FORMACION LABORAL | D8: =VLOOKUP(B8,PagosVencidos!$B$1:$H$1883,7,0)
A9: XIAOMI TECHNOLOGIES PERU S.A.C. | B9: 54590 | C9: FULLSALUD | D9: =VLOOKUP(B9,PagosVencidos!$B$1:$H$1883,7,0)
A10: DIGITAL VENTURES S.A.C. | B10: E0038653 | C10: EPS | D10: =VLOOKUP(B10,PagosVencidos!$B$1:$H$1883,7,0)
A11: DIGITAL VENTURES S.A.C. | B11: 1300364536 | C11: VIDA LEY D.L. 688 | D11: =VLOOKUP(B11,PagosVencidos!$B$1:$H$1883,7,0)
A12: XIAOMI TECHNOLOGIES PERU S.A.C. | B12: 48411 | C12: FORMACION LABORAL | D12: =VLOOKUP(B12,PagosVencidos!$B$1:$H$1883,7,0)
A13: DIGITAL BUSINESS PERU S.A.C. | B13: 67289811 | C13: VIDA LEY D.L. 688 | D13: =VLOOKUP(B13,PagosVencidos!$B$1:$H$1883,7,0)
... A465: HENN KLAUS PETER WERNER | B465: 1496943 | C465: WEB VEHICULOS | D465: =VLOOKUP(B465,PagosVencidos!$B$1:$H$1883,7,0)
